google/fhir/core/__init__.py
google/fhir/core/codes.py
google/fhir/core/extensions.py
google/fhir/core/extensions_test.py
google/fhir/core/fhir_errors.py
google/fhir/core/fhir_errors_test.py
google/fhir/core/references.py
google/fhir/core/fhir_path/FhirPathLexer.py
google/fhir/core/fhir_path/FhirPathParser.py
google/fhir/core/fhir_path/FhirPathVisitor.py
google/fhir/core/fhir_path/__init__.py
google/fhir/core/fhir_path/_ast.py
google/fhir/core/fhir_path/_ast_test.py
google/fhir/core/fhir_path/_bigquery_interpreter.py
google/fhir/core/fhir_path/_bigquery_sql_functions.py
google/fhir/core/fhir_path/_evaluation.py
google/fhir/core/fhir_path/_fhir_path_data_types.py
google/fhir/core/fhir_path/_fhir_path_data_types_test.py
google/fhir/core/fhir_path/_interpreter_test_base.py
google/fhir/core/fhir_path/_python_interpreter.py
google/fhir/core/fhir_path/_spark_interpreter.py
google/fhir/core/fhir_path/_spark_sql_functions.py
google/fhir/core/fhir_path/_sql_data_types.py
google/fhir/core/fhir_path/_sql_data_types_test.py
google/fhir/core/fhir_path/_structure_definitions.py
google/fhir/core/fhir_path/_utils.py
google/fhir/core/fhir_path/_utils_test.py
google/fhir/core/fhir_path/context.py
google/fhir/core/fhir_path/context_test.py
google/fhir/core/fhir_path/expressions.py
google/fhir/core/fhir_path/fhir_path_options.py
google/fhir/core/fhir_path/fhir_path_spark_test.py
google/fhir/core/fhir_path/fhir_path_test.py
google/fhir/core/fhir_path/fhir_path_test_base.py
google/fhir/core/fhir_path/fhir_path_validator.py
google/fhir/core/fhir_path/fhir_path_validator_test.py
google/fhir/core/fhir_path/python_compiled_expressions.py
google/fhir/core/fhir_path/quantity.py
google/fhir/core/fhir_path/quantity_test.py
google/fhir/core/internal/__init__.py
google/fhir/core/internal/_primitive_time_utils.py
google/fhir/core/internal/primitive_handler.py
google/fhir/core/internal/resource_validation.py
google/fhir/core/internal/json_format/__init__.py
google_fhir_core-0.11.0.dist-info/METADATA
google_fhir_core-0.11.0.dist-info/WHEEL
google_fhir_core-0.11.0.dist-info/top_level.txt
google_fhir_core-0.11.0.dist-info/RECORD
